imath_requests/__init__.py
imath_requests/request.py
imath_requests/server.py
imath_requests-0.3.0.dist-info/LICENSE
imath_requests-0.3.0.dist-info/METADATA
imath_requests-0.3.0.dist-info/WHEEL
imath_requests-0.3.0.dist-info/top_level.txt
imath_requests-0.3.0.dist-info/RECORD
