Metadata-Version: 2.1
Name: imath-requests
Version: 0.3.0
Summary: Communication with the iMath data platform REST API
Home-page: https://github.com/i3drobotics/imath_requests
Author: Industrial 3D Robotics
Author-email: bknight@i3drobotics.com
License: UNKNOWN
Project-URL: Documentation, https://github.com/i3drobotics/imath_requests
Project-URL: Bug Reports, https://github.com/i3drobotics/imath_requests/issues
Project-URL: Source Code, https://github.com/i3drobotics/imath_requests
Keywords: imath,i3dr,stereo,requests
Platform: UNKNOWN
Classifier: Development Status :: 3 - Alpha
Classifier: Intended Audience :: Developers
Classifier: Topic :: Software Development :: Build Tools
Classifier: Programming Language :: Python :: 3
Classifier: Programming Language :: Python :: 3.6
Classifier: Programming Language :: Python :: 3.7
Classifier: Programming Language :: Python :: 3.8
Classifier: Programming Language :: Python :: 3.9
Classifier: Programming Language :: Python :: 3 :: Only
Classifier: License :: OSI Approved :: MIT License
Classifier: Operating System :: OS Independent
Requires-Python: >=3.6
License-File: LICENSE
Requires-Dist: flask
Requires-Dist: flask-restful
Requires-Dist: requests
Provides-Extra: dev
Requires-Dist: check-manifest ; extra == 'dev'
